AUTHORS
CHANGES.markdown
COPYING
MANIFEST.in
Makefile
README.rst
isrcsubmit.bat
isrcsubmit.py
isrcsubmit.sh
setup.py
test_isrcsubmit.py
tox.ini
doc/conf.py
doc/isrcsubmit-config.5.rst
doc/isrcsubmit.1.rst
isrcsubmit.egg-info/PKG-INFO
isrcsubmit.egg-info/SOURCES.txt
isrcsubmit.egg-info/dependency_links.txt
isrcsubmit.egg-info/requires.txt
isrcsubmit.egg-info/top_level.txt
test_data/TqvKjMu7dMliSfmVEBtrL7sBSno-.pickle
test_data/TqvKjMu7dMliSfmVEBtrL7sBSno-_releases.json
test_data/hSI7B4G4AkB5.DEBcW.3KCn.D_E-.pickle
test_data/hSI7B4G4AkB5.DEBcW.3KCn.D_E-_cdrdao.toc
test_data/hSI7B4G4AkB5.DEBcW.3KCn.D_E-_releases.json