Metadata-Version: 1.1
Name: isrcsubmit
Version: 2.1.0
Summary: submit ISRCs from disc to MusicBrainz
Home-page: https://github.com/JonnyJD/musicbrainz-isrcsubmit
Author: Johannes Dewender
Author-email: brainz@JonnyJD.net
License: GPLv3+
Platform: UNKNOWN
Classifier: Development Status :: 5 - Production/Stable
Classifier: Environment :: Console
Classifier: Environment :: MacOS X
Classifier: Environment :: Win32 (MS Windows)
Classifier: Intended Audience :: End Users/Desktop
Classifier: License :: OSI Approved :: GNU General Public License v3 or later (GPLv3+)
Classifier: Operating System :: OS Independent
Classifier: Programming Language :: Python :: 2.6
Classifier: Programming Language :: Python :: 2.7
Classifier: Programming Language :: Python :: 3
Classifier: Programming Language :: Python :: 3.1
Classifier: Programming Language :: Python :: 3.2
Classifier: Programming Language :: Python :: 3.3
Classifier: Programming Language :: Python :: 3.4
Classifier: Topic :: Database :: Front-Ends
Classifier: Topic :: Multimedia :: Sound/Audio :: CD Audio :: CD Ripping
Classifier: Topic :: Text Processing :: Filters
Requires: discid(>=1.0.0)
Requires: musicbrainzngs(>=0.4)
